{
  "id": 746302481,
  "question": "明朝有几个大太监专权，比如王振，刘瑾，魏忠贤等。为什么清朝就没有？",
  "author": "山高县",
  "content": "<p>带把的奴才还真没不带把的奴才的好使，内务府比宦官坑爹多了。与清朝皇帝跟内务府斗智斗勇两百多年，稍有不慎就奴大欺主相比，明朝皇帝的日子省心多了。</p><figure data-size=\"normal\"><noscript><img src=\"https://pic1.zhimg.com/50/v2-1f099f2c41e259ddcde78b6ddffed90f_hd.jpg\" data-rawwidth=\"640\" data-rawheight=\"362\" data-size=\"normal\" data-default-watermark-src=\"https://pic2.zhimg.com/50/v2-3eea33921c81f6ecc2b4cbc636ccef1d_hd.jpg\" class=\"origin_image zh-lightbox-thumb\" width=\"640\" data-original=\"https://pic1.zhimg.com/v2-1f099f2c41e259ddcde78b6ddffed90f_r.jpg\"/></noscript><img src=\"data:image/svg+xml;utf8,&lt;svg xmlns=&#39;http://www.w3.org/2000/svg&#39; width=&#39;640&#39; height=&#39;362&#39;&gt;&lt;/svg&gt;\" data-rawwidth=\"640\" data-rawheight=\"362\" data-size=\"normal\" data-default-watermark-src=\"https://pic2.zhimg.com/50/v2-3eea33921c81f6ecc2b4cbc636ccef1d_hd.jpg\" class=\"origin_image zh-lightbox-thumb lazy\" width=\"640\" data-original=\"https://pic1.zhimg.com/v2-1f099f2c41e259ddcde78b6ddffed90f_r.jpg\" data-actualsrc=\"https://pic1.zhimg.com/50/v2-1f099f2c41e259ddcde78b6ddffed90f_hd.jpg\"/></figure><p></p>",
  "excerpt": "带把的奴才还真没不带把的奴才的好使，内务府比宦官坑爹多了。与清朝皇帝跟内务府斗智斗勇两百多年，稍有不慎就奴大欺主相比，明朝皇帝的日子省心多了。 [图片]",
  "vote": 106,
  "thanks": 12,
  "created_time": 1562917625,
  "featured_comments": [
    {
      "content": "二十两白银一个鸡蛋。[捂嘴]",
      "vote_count": 35,
      "created_time": 1562921501,
      "author": "游云",
      "reply_to_author": null
    },
    {
      "content": "内务贪，太守肥，三千太监三千贼。",
      "vote_count": 15,
      "created_time": 1562947056,
      "author": "勿言实",
      "reply_to_author": null
    },
    {
      "content": "中官无外党，精专可信任。",
      "vote_count": 20,
      "created_time": 1562917860,
      "author": "战列熊猫",
      "reply_to_author": null
    }
  ],
  "slug": "ming-zhao-you-ji-ge-da-tai-jian-zhuan-quan-bi-ru-wang-zhen-liu-jin-wei-zhong-xian-deng-wei-shi-mo-qing-zhao-jiu-mei-you-shan-gao-xian-de-hui-da",
  "title": "明朝有几个大太监专权，比如王振，刘瑾，魏忠贤等。为什么清朝就没有？-山高县的回答"
}