{
  "id": 823594564,
  "question": "如何评价美俄关系？美国为什么一定要搞垮俄罗斯？",
  "author": "山高县",
  "content": "<p>很大程度上是因为苏联统治阶级和欧美统治阶级之间没有足够的信任纽带，在欧美统治阶级看来根本不配姓伊尔根觉罗。苏联解体后的新贵，在欧美看来身份仍然是坏了规矩的暴发户，必须往死里打，杀鸡儆猴，以儆效尤。</p><p>说白了，猴子不要以为行了冠礼就算人，穷鬼不要以为在天京城里捞了两个臭钱就算贵族。</p>",
  "excerpt": "很大程度上是因为苏联统治阶级和欧美统治阶级之间没有足够的信任纽带，在欧美统治阶级看来根本不配姓伊尔根觉罗。苏联解体后的新贵，在欧美看来身份仍然是坏了规矩的暴发户，必须往死里打，杀鸡儆猴，以儆效尤。 说白了，猴子不要以为行了冠礼就算人，穷鬼不要以为在天京城里捞了两个臭钱就算贵族。",
  "vote": 272,
  "thanks": 35,
  "created_time": 1568462731,
  "featured_comments": [
    {
      "content": "挥剑击浮云，诸侯尽东来[惊喜]",
      "vote_count": 52,
      "created_time": 1568463282,
      "author": "山高县",
      "reply_to_author": "真理在上哦",
      "anchor_comments": {
        "root_comment": {
          "content": "那嵩县你觉得欧美统治阶级之间的互信还能维持多久，或者在什么情况下欧美有可能产生巨大裂痕？",
          "vote_count": 0,
          "created_time": 1568463200,
          "author": "真理在上哦",
          "reply_to_author": null
        },
        "comments": [
          {
            "content": "挥剑击浮云，诸侯尽东来[惊喜]",
            "vote_count": 52,
            "created_time": 1568463282,
            "author": "山高县",
            "reply_to_author": "真理在上哦"
          },
          {
            "content": "该评论已删除",
            "vote_count": 0,
            "created_time": 1568464603,
            "author": "于乐",
            "reply_to_author": "山高县"
          },
          {
            "content": "这玩意没法直接类比过来。特别是有立场倾向的话就会拼命找证据证明自己立场。",
            "vote_count": 1,
            "created_time": 1568465124,
            "author": "倒立倒立长颈鹿",
            "reply_to_author": "于乐"
          }
        ]
      }
    },
    {
      "content": "俄国，欧美世界中的楚国。",
      "vote_count": 31,
      "created_time": 1568463697,
      "author": "鸟之心语",
      "reply_to_author": "鸟之心语",
      "anchor_comments": {
        "root_comment": {
          "content": "我蛮夷也，不与中国之号谥。",
          "vote_count": 17,
          "created_time": 1568463334,
          "author": "鸟之心语",
          "reply_to_author": null
        },
        "comments": [
          {
            "content": "俄国，欧美世界中的楚国。",
            "vote_count": 31,
            "created_time": 1568463697,
            "author": "鸟之心语",
            "reply_to_author": "鸟之心语"
          },
          {
            "content": "<p>那本朝是？</p>",
            "vote_count": 0,
            "created_time": 1568464331,
            "author": "知乎用户",
            "reply_to_author": "鸟之心语"
          },
          {
            "content": "我是从文化角度说的，从角度上看，好像没有类似的。勉强选的话，中山国吧。",
            "vote_count": 7,
            "created_time": 1568464817,
            "author": "鸟之心语",
            "reply_to_author": "知乎用户"
          },
          {
            "content": "美哉！泱泱乎，大风也哉！",
            "vote_count": 0,
            "created_time": 1568464921,
            "author": "正在学英语",
            "reply_to_author": "知乎用户"
          },
          {
            "content": "谬哉，本朝乃天下之胡人也，不行选票之王法，不尊横竖之教化，岂敢以中原正统自居，何德与齐晋逐鹿天下",
            "vote_count": 60,
            "created_time": 1568465923,
            "author": "步云",
            "reply_to_author": "鸟之心语"
          },
          {
            "content": "中山起于白狄，学中原文化，仍被视为夷狄。[飙泪笑]",
            "vote_count": 15,
            "created_time": 1568466322,
            "author": "鸟之心语",
            "reply_to_author": "步云"
          },
          {
            "content": "中山好歹学习了中原的文化，本朝的政治和文化观念有哪个是洋人受的来的？没被六大门派围剿已经是很幸运的局面了",
            "vote_count": 18,
            "created_time": 1568466989,
            "author": "步云",
            "reply_to_author": "鸟之心语"
          },
          {
            "content": "东晋。",
            "vote_count": 0,
            "created_time": 1568466998,
            "author": "二十一世纪活匈奴",
            "reply_to_author": "知乎用户"
          },
          {
            "content": "不是很西化了吗？人大、法院、马克思主义之类。",
            "vote_count": 3,
            "created_time": 1568467120,
            "author": "鸟之心语",
            "reply_to_author": "步云"
          },
          {
            "content": "就说最基本的吧，中国人信上帝吗？",
            "vote_count": 2,
            "created_time": 1568467443,
            "author": "步云",
            "reply_to_author": "鸟之心语"
          },
          {
            "content": "你是说文化最核心的部分，语言、宗教之类的吧？那个倒确实是没有学。所以我一开始就觉得本朝不是很像中山国。日本倒是也只学了外衣。",
            "vote_count": 4,
            "created_time": 1568467877,
            "author": "鸟之心语",
            "reply_to_author": "步云"
          }
        ]
      }
    },
    {
      "content": "谬哉，本朝乃天下之胡人也，不行选票之王法，不尊横竖之教化，岂敢以中原正统自居，何德与齐晋逐鹿天下",
      "vote_count": 60,
      "created_time": 1568465923,
      "author": "步云",
      "reply_to_author": "鸟之心语",
      "anchor_comments": {
        "root_comment": {
          "content": "我蛮夷也，不与中国之号谥。",
          "vote_count": 17,
          "created_time": 1568463334,
          "author": "鸟之心语",
          "reply_to_author": null
        },
        "comments": [
          {
            "content": "俄国，欧美世界中的楚国。",
            "vote_count": 31,
            "created_time": 1568463697,
            "author": "鸟之心语",
            "reply_to_author": "鸟之心语"
          },
          {
            "content": "<p>那本朝是？</p>",
            "vote_count": 0,
            "created_time": 1568464331,
            "author": "知乎用户",
            "reply_to_author": "鸟之心语"
          },
          {
            "content": "我是从文化角度说的，从角度上看，好像没有类似的。勉强选的话，中山国吧。",
            "vote_count": 7,
            "created_time": 1568464817,
            "author": "鸟之心语",
            "reply_to_author": "知乎用户"
          },
          {
            "content": "美哉！泱泱乎，大风也哉！",
            "vote_count": 0,
            "created_time": 1568464921,
            "author": "正在学英语",
            "reply_to_author": "知乎用户"
          },
          {
            "content": "谬哉，本朝乃天下之胡人也，不行选票之王法，不尊横竖之教化，岂敢以中原正统自居，何德与齐晋逐鹿天下",
            "vote_count": 60,
            "created_time": 1568465923,
            "author": "步云",
            "reply_to_author": "鸟之心语"
          },
          {
            "content": "中山起于白狄，学中原文化，仍被视为夷狄。[飙泪笑]",
            "vote_count": 15,
            "created_time": 1568466322,
            "author": "鸟之心语",
            "reply_to_author": "步云"
          },
          {
            "content": "中山好歹学习了中原的文化，本朝的政治和文化观念有哪个是洋人受的来的？没被六大门派围剿已经是很幸运的局面了",
            "vote_count": 18,
            "created_time": 1568466989,
            "author": "步云",
            "reply_to_author": "鸟之心语"
          },
          {
            "content": "东晋。",
            "vote_count": 0,
            "created_time": 1568466998,
            "author": "二十一世纪活匈奴",
            "reply_to_author": "知乎用户"
          },
          {
            "content": "不是很西化了吗？人大、法院、马克思主义之类。",
            "vote_count": 3,
            "created_time": 1568467120,
            "author": "鸟之心语",
            "reply_to_author": "步云"
          },
          {
            "content": "就说最基本的吧，中国人信上帝吗？",
            "vote_count": 2,
            "created_time": 1568467443,
            "author": "步云",
            "reply_to_author": "鸟之心语"
          },
          {
            "content": "你是说文化最核心的部分，语言、宗教之类的吧？那个倒确实是没有学。所以我一开始就觉得本朝不是很像中山国。日本倒是也只学了外衣。",
            "vote_count": 4,
            "created_time": 1568467877,
            "author": "鸟之心语",
            "reply_to_author": "步云"
          },
          {
            "content": "不过，欧美国家的部分思想观念真的学了，只是思想观念都经历了本土化。",
            "vote_count": 10,
            "created_time": 1568467986,
            "author": "鸟之心语",
            "reply_to_author": "步云"
          },
          {
            "content": "讲道理马克思主义也是从西方学的",
            "vote_count": 8,
            "created_time": 1568468335,
            "author": "华夏英灵",
            "reply_to_author": "步云"
          },
          {
            "content": "<p>匈奴……</p>",
            "vote_count": 0,
            "created_time": 1568472294,
            "author": "达叔",
            "reply_to_author": "知乎用户"
          },
          {
            "content": "嵩县似乎一般说是后金[捂脸]",
            "vote_count": 0,
            "created_time": 1568472335,
            "author": "知乎用户",
            "reply_to_author": "达叔"
          }
        ]
      }
    },
    {
      "content": "中国比俄罗斯跟西方更不相容: 你非但信仰康米，甚至连(一神)教都不信",
      "vote_count": 66,
      "created_time": 1568466462,
      "author": "注销",
      "reply_to_author": "于乐",
      "anchor_comments": {
        "root_comment": {
          "content": "我觉得是中俄的文化中存在与西方政治现实不相容的东西",
          "vote_count": 2,
          "created_time": 1568464774,
          "author": "于乐",
          "reply_to_author": null
        },
        "comments": [
          {
            "content": "中国比俄罗斯跟西方更不相容: 你非但信仰康米，甚至连(一神)教都不信",
            "vote_count": 66,
            "created_time": 1568466462,
            "author": "注销",
            "reply_to_author": "于乐"
          },
          {
            "content": "<p>那我基本上和西方就彻底不相容了，我不光不信仰一神教（普世宗教），也十分不待见康米（普世主义）。对于我这种人，恐怕西方才是最头疼的吧？</p>",
            "vote_count": 4,
            "created_time": 1568489379,
            "author": "知乎用户",
            "reply_to_author": "注销"
          },
          {
            "content": "康米指的是Communism，如果你不信这个，对于西方来说大概也还好.....",
            "vote_count": 8,
            "created_time": 1568498881,
            "author": "注销",
            "reply_to_author": "知乎用户"
          },
          {
            "content": "信康米是西方眼中的异端好吧。信康米的黄种人，那就是异教加异端。",
            "vote_count": 11,
            "created_time": 1568510061,
            "author": "王欣瑞",
            "reply_to_author": "知乎用户"
          }
        ]
      }
    },
    {
      "content": "说白了西方也是群记吃不记打的，在钢铁洪流下瑟瑟发抖了几十年，还是没拿正眼看毛熊熊",
      "vote_count": 37,
      "created_time": 1568466570,
      "author": "注销",
      "reply_to_author": null,
      "anchor_comments": {
        "root_comment": {
          "content": "说白了西方也是群记吃不记打的，在钢铁洪流下瑟瑟发抖了几十年，还是没拿正眼看毛熊熊",
          "vote_count": 37,
          "created_time": 1568466570,
          "author": "注销",
          "reply_to_author": null
        },
        "comments": [
          {
            "content": "你的想法只能证明西方的舆论很成功，鼓动己方的民众非理性的蔑视对手，鼓动对手的民众非理性的蔑视自己本身，怎么看都是好事。跳过那些名气很大的“中国通”写的东西，找两本在欧美本土知识/政治圈里比较流行的有关中国的书籍，其中一些会让你有种错觉，ta比你还了解某些中国的特质(或许出于旁观者清的原因)。言语上轻蔑，可扣在扳机上的手可一刻都没有松懈。",
            "vote_count": 19,
            "created_time": 1568480169,
            "author": "中华儿女多奇志",
            "reply_to_author": "注销"
          },
          {
            "content": "英美与欧洲大陆不同，几百年的成功让他们进化成了既不记吃又不记打。软硬不吃奈若何？",
            "vote_count": 3,
            "created_time": 1568539403,
            "author": "火鸡进行曲",
            "reply_to_author": "注销"
          }
        ]
      }
    },
    {
      "content": "<p>嵩县果然是明白人，我很早的时候就明白一个道理了。这美国人连同样是金发碧眼的俄国人都要往死里针对。我们这帮黑发黑眼的黄种人，想来美国人是绝对不可能拿我们当自己人来看待的。</p><p>我发现三国演义或者说三国志，是一本绝对的好书。能够从里面学到许多东西。贾诩才是一个真正的明白人啊！</p>",
      "vote_count": 44,
      "created_time": 1568477356,
      "author": "天长地久终不死",
      "reply_to_author": null,
      "anchor_comments": {
        "root_comment": {
          "content": "<p>嵩县果然是明白人，我很早的时候就明白一个道理了。这美国人连同样是金发碧眼的俄国人都要往死里针对。我们这帮黑发黑眼的黄种人，想来美国人是绝对不可能拿我们当自己人来看待的。</p><p>我发现三国演义或者说三国志，是一本绝对的好书。能够从里面学到许多东西。贾诩才是一个真正的明白人啊！</p>",
          "vote_count": 44,
          "created_time": 1568477356,
          "author": "天长地久终不死",
          "reply_to_author": null
        },
        "comments": [
          {
            "content": "不是所有金发碧眼、白皮肤的白种人都能尿到一壶里去的，他们之间的矛盾冲突比我们想象的要严重得多。比如阿根廷，绝大部分都是欧洲移民后裔，却是南美中最反英美的国家之一。",
            "vote_count": 8,
            "created_time": 1568480056,
            "author": "陈宇",
            "reply_to_author": "天长地久终不死"
          },
          {
            "content": "阿根廷吗？才知道！",
            "vote_count": 1,
            "created_time": 1568533682,
            "author": "「已注销」",
            "reply_to_author": "陈宇"
          },
          {
            "content": "盎格鲁这种自诩“天命”的民族不值得信任（至少现在不值得信任），几百年的成功铸就了其“骨子”里的高傲与狂妄。",
            "vote_count": 2,
            "created_time": 1568539563,
            "author": "火鸡进行曲",
            "reply_to_author": "天长地久终不死"
          },
          {
            "content": "<p>不管是盎格鲁，还是斯拉夫。我都没兴趣理会他们各自版本的普世主义。对我来说，普世主义根本就是不可能实现的。</p><p>说难听点的，如果美国真敢搞全民直选总统的话，那么有普世主义倾向的总统候选人，一定第一个被淘汰出局。</p><a class=\"comment_sticker\" href=\"https://pic2.zhimg.com/v2-e213ddb29e5a2adb54d6343d5dea27d1.gif\" data-width=\"\" data-height=\"\">[摊手]</a>",
            "vote_count": 6,
            "created_time": 1568541114,
            "author": "天长地久终不死",
            "reply_to_author": "火鸡进行曲"
          },
          {
            "content": "那萨克森呢[捂脸]",
            "vote_count": 0,
            "created_time": 1568541222,
            "author": "「已注销」",
            "reply_to_author": "火鸡进行曲"
          },
          {
            "content": "德国人？我以为他们那是被欺负久了爆发出的民族主义把自己都洗昏了头。",
            "vote_count": 1,
            "created_time": 1568541636,
            "author": "火鸡进行曲",
            "reply_to_author": "「已注销」"
          },
          {
            "content": "理论上来说大嘤的萨克森人比盎格鲁人多，当然现在的英国人和英裔美国人不会思考自己是盎格鲁还是萨克森",
            "vote_count": 1,
            "created_time": 1568541813,
            "author": "「已注销」",
            "reply_to_author": "火鸡进行曲"
          },
          {
            "content": "只是指代，不探究真实的历史。较真的话美国现在不是一个英裔占主流的国家啊",
            "vote_count": 1,
            "created_time": 1568542029,
            "author": "火鸡进行曲",
            "reply_to_author": "「已注销」"
          },
          {
            "content": "不过你说的也没差，用昂撒也许更好一点（讲究）。",
            "vote_count": 0,
            "created_time": 1568542286,
            "author": "火鸡进行曲",
            "reply_to_author": "「已注销」"
          },
          {
            "content": "英格兰裔加德裔至少能到四十多，比凯尔特人和拉丁人还是多的",
            "vote_count": 0,
            "created_time": 1568542293,
            "author": "「已注销」",
            "reply_to_author": "火鸡进行曲"
          },
          {
            "content": "盎撒",
            "vote_count": 0,
            "created_time": 1568542303,
            "author": "火鸡进行曲",
            "reply_to_author": "「已注销」"
          },
          {
            "content": "斯拉夫是靠给蒙古人当皇协军起家的，金帐汗国之前就跟乌拉尔人种融合吸了一波寒带血了。",
            "vote_count": 2,
            "created_time": 1576672641,
            "author": "雅利安的斯芬克斯",
            "reply_to_author": "天长地久终不死"
          },
          {
            "content": "<p>虽然你我的立场不同，但我还是要说一句。像这种集合众生美好信念的理想国，真的是无法构建的。得到一部分的好处，自然也会得到一部分的坏处。从来就没有绝对有利，绝对无害这种事情。</p><p>虽然我们未必会像欧美人那样对待非洲人与美洲土著，但是不代表我们有可能会把非洲人与美洲土著当自己人来看待。泛泛之交的朋友关系，或许可以建立。但桃园三结义那样的生死之交，我不认为有建立的可能性。</p><a class=\"comment_sticker\" href=\"https://pic2.zhimg.com/v2-e213ddb29e5a2adb54d6343d5dea27d1.gif\" data-width=\"\" data-height=\"\">[摊手]</a>",
            "vote_count": 1,
            "created_time": 1576673565,
            "author": "天长地久终不死",
            "reply_to_author": "雅利安的斯芬克斯"
          },
          {
            "content": "你去了解一下日耳曼人如何血亲乱伦增殖人口再来批判隋唐苏联民族政策吧！",
            "vote_count": 2,
            "created_time": 1576675143,
            "author": "雅利安的斯芬克斯",
            "reply_to_author": "天长地久终不死"
          }
        ]
      }
    },
    {
      "content": "自从苏联解体造成三千万人非正常死亡之后，俄罗斯和美国就不可能和平了",
      "vote_count": 34,
      "created_time": 1568462967,
      "author": "不准发狗粮",
      "reply_to_author": null,
      "anchor_comments": {
        "root_comment": {
          "content": "自从苏联解体造成三千万人非正常死亡之后，俄罗斯和美国就不可能和平了",
          "vote_count": 34,
          "created_time": 1568462967,
          "author": "不准发狗粮",
          "reply_to_author": null
        },
        "comments": [
          {
            "content": "解体这么严重吗",
            "vote_count": 3,
            "created_time": 1568463461,
            "author": "建瓴",
            "reply_to_author": "不准发狗粮"
          },
          {
            "content": "内乱，内战，秩序失控，粮食紧缺",
            "vote_count": 33,
            "created_time": 1568463929,
            "author": "羅洛萊娜",
            "reply_to_author": "建瓴"
          },
          {
            "content": "可能有些夸大，但苏联解体对俄罗斯的破坏，被俄罗斯人跟蒙古入侵、德国入侵相提并论。",
            "vote_count": 43,
            "created_time": 1568463949,
            "author": "尘世清",
            "reply_to_author": "建瓴"
          },
          {
            "content": "百度冷战后东欧人口变化。。几千万人",
            "vote_count": 14,
            "created_time": 1568463966,
            "author": "气节无双我圣儒",
            "reply_to_author": "建瓴"
          },
          {
            "content": "嗯嗯，谢谢",
            "vote_count": 0,
            "created_time": 1568464231,
            "author": "建瓴",
            "reply_to_author": "气节无双我圣儒"
          },
          {
            "content": "嗯嗯，谢谢",
            "vote_count": 0,
            "created_time": 1568464238,
            "author": "建瓴",
            "reply_to_author": "羅洛萊娜"
          },
          {
            "content": "嗯嗯，谢谢",
            "vote_count": 0,
            "created_time": 1568464243,
            "author": "建瓴",
            "reply_to_author": "尘世清"
          },
          {
            "content": "可是那个不是有很多是迁移的嘛？怎么能归入非正常死亡？",
            "vote_count": 6,
            "created_time": 1568469905,
            "author": "剑啸长空",
            "reply_to_author": "气节无双我圣儒"
          },
          {
            "content": "才三千万人算啥，美国一开金口俄罗斯照样得拍屁股跟上",
            "vote_count": 0,
            "created_time": 1568470163,
            "author": "孙梓悦",
            "reply_to_author": "不准发狗粮"
          },
          {
            "content": "俄罗斯现在的人口比刚解体的时候还少，这能用移民来解释？",
            "vote_count": 2,
            "created_time": 1568480069,
            "author": "黎塞留",
            "reply_to_author": "剑啸长空"
          },
          {
            "content": "所以你以为我是什么意思？其他国家向俄罗斯移民？",
            "vote_count": 2,
            "created_time": 1568513745,
            "author": "剑啸长空",
            "reply_to_author": "黎塞留"
          }
        ]
      }
    },
    {
      "content": "我蛮夷也，不与中国之号谥。",
      "vote_count": 20,
      "created_time": 1568463334,
      "author": "鸟之心语",
      "reply_to_author": null,
      "anchor_comments": {
        "root_comment": {
          "content": "我蛮夷也，不与中国之号谥。",
          "vote_count": 20,
          "created_time": 1568463334,
          "author": "鸟之心语",
          "reply_to_author": null
        },
        "comments": [
          {
            "content": "俄国，欧美世界中的楚国。",
            "vote_count": 41,
            "created_time": 1568463697,
            "author": "鸟之心语",
            "reply_to_author": "鸟之心语"
          },
          {
            "content": "<p>那本朝是？</p>",
            "vote_count": 1,
            "created_time": 1568464331,
            "author": "逸剑飘心",
            "reply_to_author": "鸟之心语"
          },
          {
            "content": "我是从文化角度说的，从角度上看，好像没有类似的。勉强选的话，中山国吧。",
            "vote_count": 8,
            "created_time": 1568464817,
            "author": "鸟之心语",
            "reply_to_author": "逸剑飘心"
          },
          {
            "content": "美哉！泱泱乎，大风也哉！",
            "vote_count": 1,
            "created_time": 1568464921,
            "author": "正在学英语",
            "reply_to_author": "逸剑飘心"
          },
          {
            "content": "谬哉，本朝乃天下之胡人也，不行选票之王法，不尊横竖之教化，岂敢以中原正统自居，何德与齐晋逐鹿天下",
            "vote_count": 68,
            "created_time": 1568465923,
            "author": "步云",
            "reply_to_author": "鸟之心语"
          },
          {
            "content": "中山起于白狄，学中原文化，仍被视为夷狄。[飙泪笑]",
            "vote_count": 19,
            "created_time": 1568466322,
            "author": "鸟之心语",
            "reply_to_author": "步云"
          },
          {
            "content": "中山好歹学习了中原的文化，本朝的政治和文化观念有哪个是洋人受的来的？没被六大门派围剿已经是很幸运的局面了",
            "vote_count": 19,
            "created_time": 1568466989,
            "author": "步云",
            "reply_to_author": "鸟之心语"
          },
          {
            "content": "东晋。",
            "vote_count": 0,
            "created_time": 1568466998,
            "author": "二十一世纪活匈奴",
            "reply_to_author": "逸剑飘心"
          },
          {
            "content": "不是很西化了吗？人大、法院、马克思主义之类。",
            "vote_count": 4,
            "created_time": 1568467120,
            "author": "鸟之心语",
            "reply_to_author": "步云"
          },
          {
            "content": "就说最基本的吧，中国人信上帝吗？",
            "vote_count": 3,
            "created_time": 1568467443,
            "author": "步云",
            "reply_to_author": "鸟之心语"
          },
          {
            "content": "你是说文化最核心的部分，语言、宗教之类的吧？那个倒确实是没有学。所以我一开始就觉得本朝不是很像中山国。日本倒是也只学了外衣。",
            "vote_count": 5,
            "created_time": 1568467877,
            "author": "鸟之心语",
            "reply_to_author": "步云"
          },
          {
            "content": "不过，欧美国家的部分思想观念真的学了，只是思想观念都经历了本土化。",
            "vote_count": 11,
            "created_time": 1568467986,
            "author": "鸟之心语",
            "reply_to_author": "步云"
          },
          {
            "content": "讲道理马克思主义也是从西方学的",
            "vote_count": 10,
            "created_time": 1568468335,
            "author": "华夏英灵",
            "reply_to_author": "步云"
          },
          {
            "content": "<p>匈奴……</p>",
            "vote_count": 1,
            "created_time": 1568472294,
            "author": "达叔",
            "reply_to_author": "逸剑飘心"
          },
          {
            "content": "嵩县似乎一般说是后金[捂脸]",
            "vote_count": 1,
            "created_time": 1568472335,
            "author": "逸剑飘心",
            "reply_to_author": "达叔"
          },
          {
            "content": "代入明末，七大恨了解一下…我们现在也是蛮子啊[飙泪笑][飙泪笑]",
            "vote_count": 0,
            "created_time": 1568473032,
            "author": "苏嫣",
            "reply_to_author": "逸剑飘心"
          },
          {
            "content": "其实我觉得也不像匈奴，本朝没有像匈奴那样与中原王朝很不相同，但也没有像中山国那样学了很多。倒是像日本，学习了唐朝的很多东西，但仍然保持了自己的那一套语言、观念、神话、历史之类大框架，披上了一层中华文化的皮。",
            "vote_count": 7,
            "created_time": 1568474681,
            "author": "鸟之心语",
            "reply_to_author": "达叔"
          },
          {
            "content": "<p>我们不是叛出明教然后暗地里给六大派围剿光明顶帮了不少忙的天鹰教么（发呆）</p>",
            "vote_count": 5,
            "created_time": 1568596458,
            "author": "郑云娘",
            "reply_to_author": "步云"
          },
          {
            "content": "中山那是日本啊",
            "vote_count": 0,
            "created_time": 1568637994,
            "author": "贰师城下汗血马",
            "reply_to_author": "鸟之心语"
          },
          {
            "content": "蒙古。。",
            "vote_count": 0,
            "created_time": 1570212602,
            "author": "武起",
            "reply_to_author": "鸟之心语"
          }
        ]
      }
    }
  ],
  "slug": "ru-he-ping-jia-mei-e-guan-xi-mei-guo-wei-shi-mo-yi-ding-yao-gao-kua-e-luo-si-shan-gao-xian-de-hui-da",
  "title": "如何评价美俄关系？美国为什么一定要搞垮俄罗斯？-山高县的回答"
}