{
  "id": 920678009,
  "question": "中国可不可以走一条不靠中产阶级崛起的路？",
  "author": "山高县",
  "content": "<p>海东青和高丽参确实是建州经济的支柱，007式的蹲鹰和挖参虽然苦，但在建州也是让绝大多数摸鱼诸申羡慕的好工作。然而蹲鹰和挖参，改变不了摸鱼是绝大多数女真年轻人唯一出路的现实。建州固然不可能靠摸鱼崛起，更不可能靠蹲海边抓海东青和钻长白山挖高丽参而崛起啊。</p><p>“宁为一步甲，胜做挖参人”。。。。</p>",
  "excerpt": "海东青和高丽参确实是建州经济的支柱，007式的蹲鹰和挖参虽然苦，但在建州也是让绝大多数摸鱼诸申羡慕的好工作。然而蹲鹰和挖参，改变不了摸鱼是绝大多数女真年轻人唯一出路的现实。建州固然不可能靠摸鱼崛起，更不可能靠蹲海边抓海东青和钻长白山挖高丽参而崛起啊。 “宁为一步甲，胜做挖参人”。。。",
  "vote": 473,
  "thanks": 52,
  "created_time": 1575355919,
  "featured_comments": [
    {
      "content": "今日入关(1/1）",
      "vote_count": 137,
      "created_time": 1575355961,
      "author": "知乎用户",
      "reply_to_author": null,
      "anchor_comments": {
        "root_comment": {
          "content": "今日入关(1/1）",
          "vote_count": 137,
          "created_time": 1575355961,
          "author": "知乎用户",
          "reply_to_author": null
        },
        "comments": [
          {
            "content": "今日扩核",
            "vote_count": 0,
            "created_time": 1575389878,
            "author": "李察",
            "reply_to_author": "Marcovaldo"
          }
        ]
      }
    },
    {
      "content": "入关 一切为了入关",
      "vote_count": 35,
      "created_time": 1575356082,
      "author": "无里克里",
      "reply_to_author": null
    },
    {
      "content": "新说明亡清兴六十年——嵩县著",
      "vote_count": 222,
      "created_time": 1575356083,
      "author": "ChiuChveh",
      "reply_to_author": null
    },
    {
      "content": "确实那些很重要，可是这些东西本质上是贱价贩卖本国的劳动力。关键是，一直贱卖本国劳动力并不能致富。",
      "vote_count": 195,
      "created_time": 1575356184,
      "author": "samdarsana",
      "reply_to_author": null,
      "anchor_comments": {
        "root_comment": {
          "content": "确实那些很重要，可是这些东西本质上是贱价贩卖本国的劳动力。关键是，一直贱卖本国劳动力并不能致富。",
          "vote_count": 195,
          "created_time": 1575356184,
          "author": "samdarsana",
          "reply_to_author": null
        },
        "comments": [
          {
            "content": "有成功的经验，如果工业化早，一是殖民地，二是奴隶制。等发展起来，通过洗地可以美化自己发展史。<br>如果工业化晚，人口还多没法靠卖资源致富，又不肯卖劳动力，那凭什么你能弥补差距而崛起。",
            "vote_count": 54,
            "created_time": 1575358683,
            "author": "Micheal Du",
            "reply_to_author": "samdarsana"
          },
          {
            "content": "那和原住民有什么关系呢？",
            "vote_count": 9,
            "created_time": 1575359400,
            "author": "黎塞留",
            "reply_to_author": "Micheal Du"
          },
          {
            "content": "发展规律就是这样子的，谁能改变？除非直接不发展。你的问题是分配问题。",
            "vote_count": 1,
            "created_time": 1575360201,
            "author": "张骏",
            "reply_to_author": "黎塞留"
          },
          {
            "content": "原住民只能按温铁军的观点内部掠夺，类似于剪刀差等",
            "vote_count": 16,
            "created_time": 1575360233,
            "author": "darkwingsxx",
            "reply_to_author": "黎塞留"
          },
          {
            "content": "<p>无一不是，这真的是规律，毕竟发展需要的矿可不是凭空变出来的</p>",
            "vote_count": 7,
            "created_time": 1575366346,
            "author": "敲扁土豆",
            "reply_to_author": "darkwingsxx"
          },
          {
            "content": "<p>呵呵，你还没有摸到，技术等价资源，人权就是市场这一定律啊。不怪你。</p>",
            "vote_count": 0,
            "created_time": 1575380033,
            "author": "阿甘",
            "reply_to_author": "Micheal Du"
          },
          {
            "content": "<p>凭50/60/70，也就是爷辈与父辈，尤其是他们中的农民的巨大牺牲。是一个人用身先士卒与伟大理想带领他们去为这个国家的后代做出牺牲。</p>",
            "vote_count": 1,
            "created_time": 1581837059,
            "author": "Tiamat",
            "reply_to_author": "Micheal Du"
          }
        ]
      }
    },
    {
      "content": "拿着敕书卖参赚钱，才能买三国演义学兵法。",
      "vote_count": 121,
      "created_time": 1575356241,
      "author": "战列熊猫",
      "reply_to_author": null,
      "anchor_comments": {
        "root_comment": {
          "content": "拿着敕书卖参赚钱，才能买三国演义学兵法。",
          "vote_count": 121,
          "created_time": 1575356241,
          "author": "战列熊猫",
          "reply_to_author": null
        },
        "comments": [
          {
            "content": "得先卖给叶赫[生气][生气]",
            "vote_count": 107,
            "created_time": 1575356291,
            "author": "山高县",
            "reply_to_author": "战列熊猫"
          },
          {
            "content": "不仅需要兵法还需要火药和红衣大炮。",
            "vote_count": 12,
            "created_time": 1575356322,
            "author": "samdarsana",
            "reply_to_author": "战列熊猫"
          },
          {
            "content": "乌真超哈兵那都是皇太极时期才有的。努尔哈赤大汗铠甲十三就能起兵。",
            "vote_count": 34,
            "created_time": 1575356510,
            "author": "战列熊猫",
            "reply_to_author": "samdarsana"
          },
          {
            "content": "嵩县有时间详细写下瓜分大英的狂潮的时间线和过程么？",
            "vote_count": 7,
            "created_time": 1575359778,
            "author": "Leviathan",
            "reply_to_author": "山高县"
          },
          {
            "content": "叶赫现在是大明的好狗啊",
            "vote_count": 13,
            "created_time": 1575359907,
            "author": "ufo",
            "reply_to_author": "山高县"
          },
          {
            "content": "大体如此：<br>抗日：长江流域。<br>绥靖与苏德互不侵犯—东欧。<br>海岛换军舰—割让西加勒比及南美。<br>大西洋宪章—帝国死缓。<br>印度独立—失去皇冠。<br>关贸总协定及森林协议—失去国际货币和大英统一市场。<br>苏伊士运河事变—死刑执行，告别中东及苏伊士以东，殖民地独立狂潮。<br>加入欧共体—放弃帝国特惠制，帝国的棺材加盖。<br>狙击英镑—大英百年财富。。。。。",
            "vote_count": 77,
            "created_time": 1575360386,
            "author": "山高县",
            "reply_to_author": "Leviathan"
          },
          {
            "content": "建州有那么多挖宝养鹰的文化人小清新天天威胁战胜国反思德三，狙击“军国主义”马？急求答案，来来认真点[谢邀]",
            "vote_count": 10,
            "created_time": 1575370244,
            "author": "寒江雪",
            "reply_to_author": "山高县"
          },
          {
            "content": "我叶赫300敕书都是女人换的么？不，还有用男孩子换的",
            "vote_count": 0,
            "created_time": 1575371389,
            "author": "亲爱的曦哥",
            "reply_to_author": "山高县"
          },
          {
            "content": "嵩县能推荐几本军事理论书吗",
            "vote_count": 0,
            "created_time": 1575391335,
            "author": "冰格JIE",
            "reply_to_author": "山高县"
          },
          {
            "content": "叶赫指哪位啊，求解",
            "vote_count": 0,
            "created_time": 1577204227,
            "author": "linting",
            "reply_to_author": "山高县"
          },
          {
            "content": "湾湾",
            "vote_count": 0,
            "created_time": 1584596271,
            "author": "故梦",
            "reply_to_author": "linting"
          }
        ]
      }
    },
    {
      "content": "得先卖给叶赫[生气][生气]",
      "vote_count": 106,
      "created_time": 1575356291,
      "author": "山高县",
      "reply_to_author": "战列熊猫",
      "anchor_comments": {
        "root_comment": {
          "content": "拿着敕书卖参赚钱，才能买三国演义学兵法。",
          "vote_count": 122,
          "created_time": 1575356241,
          "author": "战列熊猫",
          "reply_to_author": null
        },
        "comments": [
          {
            "content": "得先卖给叶赫[生气][生气]",
            "vote_count": 107,
            "created_time": 1575356291,
            "author": "山高县",
            "reply_to_author": "战列熊猫"
          },
          {
            "content": "不仅需要兵法还需要火药和红衣大炮。",
            "vote_count": 12,
            "created_time": 1575356322,
            "author": "samdarsana",
            "reply_to_author": "战列熊猫"
          },
          {
            "content": "乌真超哈兵那都是皇太极时期才有的。努尔哈赤大汗铠甲十三就能起兵。",
            "vote_count": 34,
            "created_time": 1575356510,
            "author": "战列熊猫",
            "reply_to_author": "samdarsana"
          },
          {
            "content": "嵩县有时间详细写下瓜分大英的狂潮的时间线和过程么？",
            "vote_count": 7,
            "created_time": 1575359778,
            "author": "Leviathan",
            "reply_to_author": "山高县"
          },
          {
            "content": "叶赫现在是大明的好狗啊",
            "vote_count": 13,
            "created_time": 1575359907,
            "author": "ufo",
            "reply_to_author": "山高县"
          },
          {
            "content": "大体如此：<br>抗日：长江流域。<br>绥靖与苏德互不侵犯—东欧。<br>海岛换军舰—割让西加勒比及南美。<br>大西洋宪章—帝国死缓。<br>印度独立—失去皇冠。<br>关贸总协定及森林协议—失去国际货币和大英统一市场。<br>苏伊士运河事变—死刑执行，告别中东及苏伊士以东，殖民地独立狂潮。<br>加入欧共体—放弃帝国特惠制，帝国的棺材加盖。<br>狙击英镑—大英百年财富。。。。。",
            "vote_count": 77,
            "created_time": 1575360386,
            "author": "山高县",
            "reply_to_author": "Leviathan"
          },
          {
            "content": "建州有那么多挖宝养鹰的文化人小清新天天威胁战胜国反思德三，狙击“军国主义”马？急求答案，来来认真点[谢邀]",
            "vote_count": 10,
            "created_time": 1575370244,
            "author": "寒江雪",
            "reply_to_author": "山高县"
          },
          {
            "content": "我叶赫300敕书都是女人换的么？不，还有用男孩子换的",
            "vote_count": 0,
            "created_time": 1575371389,
            "author": "亲爱的曦哥",
            "reply_to_author": "山高县"
          },
          {
            "content": "嵩县能推荐几本军事理论书吗",
            "vote_count": 0,
            "created_time": 1575391335,
            "author": "冰格JIE",
            "reply_to_author": "山高县"
          },
          {
            "content": "叶赫指哪位啊，求解",
            "vote_count": 0,
            "created_time": 1577204227,
            "author": "linting",
            "reply_to_author": "山高县"
          },
          {
            "content": "湾湾",
            "vote_count": 0,
            "created_time": 1584596271,
            "author": "故梦",
            "reply_to_author": "linting"
          }
        ]
      }
    },
    {
      "content": "乌真超哈兵那都是皇太极时期才有的。努尔哈赤大汗铠甲十三就能起兵。",
      "vote_count": 34,
      "created_time": 1575356510,
      "author": "战列熊猫",
      "reply_to_author": "samdarsana",
      "anchor_comments": {
        "root_comment": {
          "content": "拿着敕书卖参赚钱，才能买三国演义学兵法。",
          "vote_count": 122,
          "created_time": 1575356241,
          "author": "战列熊猫",
          "reply_to_author": null
        },
        "comments": [
          {
            "content": "得先卖给叶赫[生气][生气]",
            "vote_count": 107,
            "created_time": 1575356291,
            "author": "山高县",
            "reply_to_author": "战列熊猫"
          },
          {
            "content": "不仅需要兵法还需要火药和红衣大炮。",
            "vote_count": 12,
            "created_time": 1575356322,
            "author": "samdarsana",
            "reply_to_author": "战列熊猫"
          },
          {
            "content": "乌真超哈兵那都是皇太极时期才有的。努尔哈赤大汗铠甲十三就能起兵。",
            "vote_count": 34,
            "created_time": 1575356510,
            "author": "战列熊猫",
            "reply_to_author": "samdarsana"
          },
          {
            "content": "嵩县有时间详细写下瓜分大英的狂潮的时间线和过程么？",
            "vote_count": 7,
            "created_time": 1575359778,
            "author": "Leviathan",
            "reply_to_author": "山高县"
          },
          {
            "content": "叶赫现在是大明的好狗啊",
            "vote_count": 13,
            "created_time": 1575359907,
            "author": "ufo",
            "reply_to_author": "山高县"
          },
          {
            "content": "大体如此：<br>抗日：长江流域。<br>绥靖与苏德互不侵犯—东欧。<br>海岛换军舰—割让西加勒比及南美。<br>大西洋宪章—帝国死缓。<br>印度独立—失去皇冠。<br>关贸总协定及森林协议—失去国际货币和大英统一市场。<br>苏伊士运河事变—死刑执行，告别中东及苏伊士以东，殖民地独立狂潮。<br>加入欧共体—放弃帝国特惠制，帝国的棺材加盖。<br>狙击英镑—大英百年财富。。。。。",
            "vote_count": 77,
            "created_time": 1575360386,
            "author": "山高县",
            "reply_to_author": "Leviathan"
          },
          {
            "content": "建州有那么多挖宝养鹰的文化人小清新天天威胁战胜国反思德三，狙击“军国主义”马？急求答案，来来认真点[谢邀]",
            "vote_count": 10,
            "created_time": 1575370244,
            "author": "寒江雪",
            "reply_to_author": "山高县"
          },
          {
            "content": "我叶赫300敕书都是女人换的么？不，还有用男孩子换的",
            "vote_count": 0,
            "created_time": 1575371389,
            "author": "亲爱的曦哥",
            "reply_to_author": "山高县"
          },
          {
            "content": "嵩县能推荐几本军事理论书吗",
            "vote_count": 0,
            "created_time": 1575391335,
            "author": "冰格JIE",
            "reply_to_author": "山高县"
          },
          {
            "content": "叶赫指哪位啊，求解",
            "vote_count": 0,
            "created_time": 1577204227,
            "author": "linting",
            "reply_to_author": "山高县"
          },
          {
            "content": "湾湾",
            "vote_count": 0,
            "created_time": 1584596271,
            "author": "故梦",
            "reply_to_author": "linting"
          }
        ]
      }
    },
    {
      "content": "十三个特混集团军群起兵[惊喜][惊喜][惊喜]",
      "vote_count": 104,
      "created_time": 1575356907,
      "author": "先出无尽",
      "reply_to_author": null,
      "anchor_comments": {
        "root_comment": {
          "content": "十三个特混集团军群起兵[惊喜][惊喜][惊喜]",
          "vote_count": 104,
          "created_time": 1575356907,
          "author": "先出无尽",
          "reply_to_author": null
        },
        "comments": [
          {
            "content": "天   诛",
            "vote_count": 3,
            "created_time": 1575370270,
            "author": "荒原生",
            "reply_to_author": "先出无尽"
          },
          {
            "content": "<p>十三个核动力CV特混编队[雾]</p>",
            "vote_count": 6,
            "created_time": 1575424066,
            "author": "杜周安",
            "reply_to_author": "先出无尽"
          }
        ]
      }
    },
    {
      "content": "为了让多数天朝人用的上曹学，需要先使用嵩学[惊喜]",
      "vote_count": 43,
      "created_time": 1575357846,
      "author": "疾风Jager",
      "reply_to_author": "今夜的风好喧嚣",
      "anchor_comments": {
        "root_comment": {
          "content": "看起来是曹嵩合流，实际上嵩学是曹学的升级版",
          "vote_count": 17,
          "created_time": 1575357479,
          "author": "今夜的风好喧嚣",
          "reply_to_author": null
        },
        "comments": [
          {
            "content": "为了让多数天朝人用的上曹学，需要先使用嵩学[惊喜]",
            "vote_count": 43,
            "created_time": 1575357846,
            "author": "疾风Jager",
            "reply_to_author": "今夜的风好喧嚣"
          },
          {
            "content": "<p>曹是平城思想，嵩县这是昭和御魂。看似一体，实则两面。</p>",
            "vote_count": 55,
            "created_time": 1575359283,
            "author": "知乎用户",
            "reply_to_author": "今夜的风好喧嚣"
          },
          {
            "content": "曹学提供哲学理论，嵩学提供操作手段[惊喜]",
            "vote_count": 1,
            "created_time": 1576052494,
            "author": "尼古拉斯·一饼",
            "reply_to_author": "疾风Jager"
          }
        ]
      }
    },
    {
      "content": "有成功的经验，如果工业化早，一是殖民地，二是奴隶制。等发展起来，通过洗地可以美化自己发展史。<br>如果工业化晚，人口还多没法靠卖资源致富，又不肯卖劳动力，那凭什么你能弥补差距而崛起。",
      "vote_count": 54,
      "created_time": 1575358683,
      "author": "知乎用户",
      "reply_to_author": "samdarsana",
      "anchor_comments": {
        "root_comment": {
          "content": "确实那些很重要，可是这些东西本质上是贱价贩卖本国的劳动力。关键是，一直贱卖本国劳动力并不能致富。",
          "vote_count": 195,
          "created_time": 1575356184,
          "author": "samdarsana",
          "reply_to_author": null
        },
        "comments": [
          {
            "content": "有成功的经验，如果工业化早，一是殖民地，二是奴隶制。等发展起来，通过洗地可以美化自己发展史。<br>如果工业化晚，人口还多没法靠卖资源致富，又不肯卖劳动力，那凭什么你能弥补差距而崛起。",
            "vote_count": 54,
            "created_time": 1575358683,
            "author": "知乎用户",
            "reply_to_author": "samdarsana"
          },
          {
            "content": "那和原住民有什么关系呢？",
            "vote_count": 9,
            "created_time": 1575359400,
            "author": "黎塞留",
            "reply_to_author": "知乎用户"
          },
          {
            "content": "发展规律就是这样子的，谁能改变？除非直接不发展。你的问题是分配问题。",
            "vote_count": 1,
            "created_time": 1575360201,
            "author": "张骏",
            "reply_to_author": "黎塞留"
          },
          {
            "content": "原住民只能按温铁军的观点内部掠夺，类似于剪刀差等",
            "vote_count": 16,
            "created_time": 1575360233,
            "author": "darkwingsxx",
            "reply_to_author": "黎塞留"
          },
          {
            "content": "<p>无一不是，这真的是规律，毕竟发展需要的矿可不是凭空变出来的</p>",
            "vote_count": 7,
            "created_time": 1575366346,
            "author": "敲扁土豆",
            "reply_to_author": "darkwingsxx"
          },
          {
            "content": "<p>呵呵，你还没有摸到，技术等价资源，人权就是市场这一定律啊。不怪你。</p>",
            "vote_count": 0,
            "created_time": 1575380033,
            "author": "阿甘",
            "reply_to_author": "知乎用户"
          },
          {
            "content": "<p>凭50/60/70，也就是爷辈与父辈，尤其是他们中的农民的巨大牺牲。是一个人用身先士卒与伟大理想带领他们去为这个国家的后代做出牺牲。</p>",
            "vote_count": 1,
            "created_time": 1581837059,
            "author": "Tiamat",
            "reply_to_author": "知乎用户"
          }
        ]
      }
    },
    {
      "content": "新说明亡清兴六十年——嵩县著",
      "vote_count": 241,
      "created_time": 1575356083,
      "author": "ChiuChveh",
      "reply_to_author": null
    },
    {
      "content": "确实那些很重要，可是这些东西本质上是贱价贩卖本国的劳动力。关键是，一直贱卖本国劳动力并不能致富。",
      "vote_count": 212,
      "created_time": 1575356184,
      "author": "samdarsana",
      "reply_to_author": null,
      "anchor_comments": {
        "root_comment": {
          "content": "确实那些很重要，可是这些东西本质上是贱价贩卖本国的劳动力。关键是，一直贱卖本国劳动力并不能致富。",
          "vote_count": 212,
          "created_time": 1575356184,
          "author": "samdarsana",
          "reply_to_author": null
        },
        "comments": [
          {
            "content": "有成功的经验，如果工业化早，一是殖民地，二是奴隶制。等发展起来，通过洗地可以美化自己发展史。<br>如果工业化晚，人口还多没法靠卖资源致富，又不肯卖劳动力，那凭什么你能弥补差距而崛起。",
            "vote_count": 61,
            "created_time": 1575358683,
            "author": "Micheal Du",
            "reply_to_author": "samdarsana"
          },
          {
            "content": "那和原住民有什么关系呢？",
            "vote_count": 10,
            "created_time": 1575359400,
            "author": "黎塞留",
            "reply_to_author": "Micheal Du"
          },
          {
            "content": "发展规律就是这样子的，谁能改变？除非直接不发展。你的问题是分配问题。",
            "vote_count": 3,
            "created_time": 1575360201,
            "author": "「已注销」",
            "reply_to_author": "黎塞留"
          },
          {
            "content": "原住民只能按温铁军的观点内部掠夺，类似于剪刀差等",
            "vote_count": 18,
            "created_time": 1575360233,
            "author": "darkwingsxx",
            "reply_to_author": "黎塞留"
          },
          {
            "content": "<p>无一不是，这真的是规律，毕竟发展需要的矿可不是凭空变出来的</p>",
            "vote_count": 9,
            "created_time": 1575366346,
            "author": "敲扁土豆",
            "reply_to_author": "darkwingsxx"
          },
          {
            "content": "<p>呵呵，你还没有摸到，技术等价资源，人权就是市场这一定律啊。不怪你。</p>",
            "vote_count": 2,
            "created_time": 1575380033,
            "author": "Andy",
            "reply_to_author": "Micheal Du"
          },
          {
            "content": "<p>凭50/60/70，也就是爷辈与父辈，尤其是他们中的农民的巨大牺牲。是一个人用身先士卒与伟大理想带领他们去为这个国家的后代做出牺牲。</p>",
            "vote_count": 2,
            "created_time": 1581837059,
            "author": "Tiamat",
            "reply_to_author": "Micheal Du"
          }
        ]
      }
    },
    {
      "content": "入关不能解决所有问题，但是能解决问题。某些建州读经念经的也是傻的没有危机感。入关后自有江南儒学大师给清廷写经。谁还看得上他们那些石头脑壳的二道贩子。",
      "vote_count": 80,
      "created_time": 1575359512,
      "author": "林观",
      "reply_to_author": null
    },
    {
      "content": "该评论已删除",
      "vote_count": 71,
      "created_time": 1575356365,
      "author": "「已注销」",
      "reply_to_author": null,
      "anchor_comments": {
        "root_comment": {
          "content": "该评论已删除",
          "vote_count": 71,
          "created_time": 1575356365,
          "author": "「已注销」",
          "reply_to_author": null
        },
        "comments": [
          {
            "content": "私以为叫天使投资不合适，中了大明某些人“大明重建了建州”歪论的套。理所应当的自由贸易权利居然能被当做奖赏，集中体现了大明帝国主义治下国际关系体系的压迫本质，不平等就在这里啊。",
            "vote_count": 40,
            "created_time": 1575382997,
            "author": "「已注销」",
            "reply_to_author": "「已注销」"
          },
          {
            "content": "你我学术成就不分伯仲",
            "vote_count": 7,
            "created_time": 1575428741,
            "author": "「已注销」",
            "reply_to_author": "「已注销」"
          }
        ]
      }
    },
    {
      "content": "皇国ノ兴廃此ノ一戦ニ在リ、各员一层奋励努力セヨ",
      "vote_count": 23,
      "created_time": 1575356441,
      "author": "vertigopbd",
      "reply_to_author": null
    },
    {
      "content": "好一个“宁为一步甲，胜做挖参人”",
      "vote_count": 21,
      "created_time": 1575357788,
      "author": "诸葛之风",
      "reply_to_author": null
    }
  ],
  "slug": "zhong-guo-ke-bu-ke-yi-zou-yi-tiao-bu-kao-zhong-chan-jie-ji-jue-qi-de-lu-shan-gao-xian-de-hui-da",
  "title": "中国可不可以走一条不靠中产阶级崛起的路？-山高县的回答"
}